langgraph_store_dynamodb/LICENSE
langgraph_store_dynamodb/__init__.py
langgraph_store_dynamodb/dynamodbStore.py
langgraph_store_dynamodb-0.1.4.dist-info/METADATA
langgraph_store_dynamodb-0.1.4.dist-info/WHEEL
langgraph_store_dynamodb-0.1.4.dist-info/RECORD
