Metadata-Version: 2.4
Name: langgraph_store_dynamodb
Version: 0.1.4
Summary: DynamoDB dtore for LangGraph
Project-URL: Repository, https://github.com/skamalj/langgraph_store_dynamodb.git
Author-email: Kamal <skamalj@github.com>
Classifier: License :: OSI Approved :: MIT License
Classifier: Operating System :: OS Independent
Classifier: Programming Language :: Python :: 3
Requires-Python: >=3.9
Requires-Dist: aioboto3>=13.3.0
Requires-Dist: boto3>=1.35.81
Requires-Dist: botocore>=1.35.81
Requires-Dist: langchain-core>=0.3.28
Requires-Dist: langgraph>=0.2.60
Provides-Extra: dev
Requires-Dist: black; extra == 'dev'
Requires-Dist: isort; extra == 'dev'
Requires-Dist: mypy; extra == 'dev'
Requires-Dist: pytest-cov; extra == 'dev'
Requires-Dist: pytest>=7.0; extra == 'dev'
